{
    "external_urls": {
        "spotify": "https://open.spotify.com/artist/7kplJl06UmldxLKseURAYi"
    },
    "followers": {
        "href": null,
        "total": 706191
    },
    "genres": [
        "modern country pop"
    ],
    "href": "https://api.spotify.com/v1/artists/7kplJl06UmldxLKseURAYi",
    "id": "7kplJl06UmldxLKseURAYi",
    "images": [
        {
            "height": 640,
            "url": "https://i.scdn.co/image/ab6761610000e5eb3d137b5c8613610be552b2d3",
            "width": 640
        },
        {
            "height": 320,
            "url": "https://i.scdn.co/image/ab676161000051743d137b5c8613610be552b2d3",
            "width": 320
        },
        {
            "height": 160,
            "url": "https://i.scdn.co/image/ab6761610000f1783d137b5c8613610be552b2d3",
            "width": 160
        }
    ],
    "name": "Warren Zeiders",
    "popularity": 72,
    "type": "artist",
    "uri": "spotify:artist:7kplJl06UmldxLKseURAYi"
}