{
    "external_urls": {
        "spotify": "https://open.spotify.com/artist/6zLBxLdl60ekBLpawtT63I"
    },
    "followers": {
        "href": null,
        "total": 1363299
    },
    "genres": [
        "classic texas country",
        "contemporary country",
        "modern country pop"
    ],
    "href": "https://api.spotify.com/v1/artists/6zLBxLdl60ekBLpawtT63I",
    "id": "6zLBxLdl60ekBLpawtT63I",
    "images": [
        {
            "height": 640,
            "url": "https://i.scdn.co/image/ab6761610000e5eb37fd77080cfc361e8f61337c",
            "width": 640
        },
        {
            "height": 320,
            "url": "https://i.scdn.co/image/ab6761610000517437fd77080cfc361e8f61337c",
            "width": 320
        },
        {
            "height": 160,
            "url": "https://i.scdn.co/image/ab6761610000f17837fd77080cfc361e8f61337c",
            "width": 160
        }
    ],
    "name": "Cody Johnson",
    "popularity": 75,
    "type": "artist",
    "uri": "spotify:artist:6zLBxLdl60ekBLpawtT63I"
}